upnlp/__init__.py
upnlp/lm_models.py
upnlp/nlp_datasets.py
upnlp/requirements.txt
upnlp/tokenizers.py
upnlp/trainer.py
upnlp/word_views.py
upnlp-0.0.12.dist-info/LICENSE
upnlp-0.0.12.dist-info/METADATA
upnlp-0.0.12.dist-info/WHEEL
upnlp-0.0.12.dist-info/top_level.txt
upnlp-0.0.12.dist-info/RECORD
