Metadata-Version: 2.1
Name: upnlp
Version: 0.0.12
Summary: A package designed to support NLP teaching at graduate level
Author-email: Benoit Crabbé <benoit.crabbe@u-paris.fr>
Project-URL: Homepage, https://github.com/bencrabbe/upc-nlp
Project-URL: Issues, https://github.com/bencrabbe/upc-nlp/issues
Classifier: Programming Language :: Python :: 3
Classifier: License :: OSI Approved :: GNU General Public License v3 (GPLv3)
Classifier: Operating System :: OS Independent
Classifier: Topic :: Text Processing :: Linguistic
Classifier: Topic :: Scientific/Engineering :: Human Machine Interfaces
Requires-Python: >=3.10
License-File: LICENSE
Requires-Dist: inflect
Requires-Dist: optuna
Requires-Dist: PyYAML
Requires-Dist: Requests
Requires-Dist: torch
Requires-Dist: tqdm
Requires-Dist: wn
Requires-Dist: pandas
Requires-Dist: umap-learn
Requires-Dist: bpemb
